pycaptcha/__init__.py
pycaptcha/harvester.py
pycaptcha/scripts.py
xcap-1.0.dist-info/LICENSE
xcap-1.0.dist-info/METADATA
xcap-1.0.dist-info/WHEEL
xcap-1.0.dist-info/top_level.txt
xcap-1.0.dist-info/RECORD
